COPYRIGHT
MANIFEST.in
Makefile
README
mangler.py
setup.py
test/__init__.py
test/__init__.pyc
test/test_union_filter.py
test/test_union_filter.pyc
tiddlywebplugins/__init__.py
tiddlywebplugins/oom.py
tiddlywebplugins.oom.egg-info/PKG-INFO
tiddlywebplugins.oom.egg-info/SOURCES.txt
tiddlywebplugins.oom.egg-info/dependency_links.txt
tiddlywebplugins.oom.egg-info/namespace_packages.txt
tiddlywebplugins.oom.egg-info/not-zip-safe
tiddlywebplugins.oom.egg-info/requires.txt
tiddlywebplugins.oom.egg-info/top_level.txt