Metadata-Version: 1.0
Name: tiddlywebplugins.oom
Version: 0.5
Summary: A TiddlyWeb plugin providing a one of many select filter.
Home-page: http://pypi.python.org/pypi/tiddlywebplugins.oom
Author: Chris Dent
Author-email: cdent@peermore.com
License: BSD
Platform: Posix; MacOS X; Windows
